cli/__init__.py
cli/main.py
cli/commands/__init__.py
cli/commands/collection.py
cli/commands/proxy.py
cli/components/__init__.py
cli/components/interactive_table.py
simulchip/__init__.py
simulchip/cache.py
simulchip/cli_utils.py
simulchip/comparison.py
simulchip/display.py
simulchip/filters.py
simulchip/interactive.py
simulchip/models.py
simulchip/paths.py
simulchip/platform.py
simulchip/terminal_images.py
simulchip/utils.py
simulchip/api/__init__.py
simulchip/api/netrunnerdb.py
simulchip/collection/__init__.py
simulchip/collection/manager.py
simulchip/collection/operations.py
simulchip/pdf/__init__.py
simulchip/pdf/generator.py
simulchip-0.1.7.dist-info/licenses/LICENSE
simulchip-0.1.7.dist-info/METADATA
simulchip-0.1.7.dist-info/WHEEL
simulchip-0.1.7.dist-info/entry_points.txt
simulchip-0.1.7.dist-info/top_level.txt
simulchip-0.1.7.dist-info/RECORD
